{
    "exports": {
        "alt": "alt__77d89",
        "emptyResultsContent": "emptyResultsContent_d2d74a",
        "emptyResultsText": "emptyResultsText__7b64d",
        "emptyResultsWrap": "emptyResultsWrap__0d55d",
        "errorImage": "errorImage__3570d",
        "errorMessage": "errorMessage__8ee6a",
        "noResults": "noResults__0019c",
        "noResultsImage": "noResultsImage__1a10e",
        "scroller": "scroller__5f036",
        "searchResultsWrap": "searchResultsWrap__2e184",
        "stillIndexing": "stillIndexing__839ed"
    }
}