{
    "exports": {
        "acked": "acked__4f17a",
        "badge": "badge__1b0e6",
        "badgeContainer": "badgeContainer__9dee3",
        "buttons": "buttons__9634c",
        "card": "card_a166d0",
        "clickable": "clickable__3448a",
        "discount": "discount__3de26",
        "expired": "expired_ebed2c",
        "gradientWrapperTier0": "gradientWrapperTier0__561ec",
        "gradientWrapperTier2": "gradientWrapperTier2_d1e63f",
        "icon": "icon__05415",
        "idRow": "idRow__3f6d3",
        "input": "input__8cdc1",
        "inputRow": "inputRow__43571",
        "isLoading": "isLoading_a12abd",
        "loadingContainer": "loadingContainer__5cfcb",
        "nameRow": "nameRow_cffdbb",
        "noMargin": "noMargin__35f8a",
        "panelInner": "panelInner_b9781a",
        "redeemed": "redeemed_d65a17",
        "row": "row_ef488f",
        "section": "section__7585a",
        "trashIcon": "trashIcon_a93ee7"
    }
}