{
    "exports": {
        "appIcon": "appIcon__28528",
        "appIconBorderThingy": "appIconBorderThingy_ae30b7",
        "appName": "appName_ebbaf1",
        "command": "command__50216",
        "commandListHeader": "commandListHeader__7a030",
        "commandName": "commandName__449f8",
        "container": "container__7b73b",
        "contentContainer": "contentContainer_d17a62",
        "headerCloseButton": "headerCloseButton_d793f6",
        "headerWhenSideCard": "headerWhenSideCard__74c6c",
        "sortSelector": "sortSelector_afb34f"
    }
}