{
    "exports": {
        "default": {
            "calendar": "Календар",
            "day": "ден",
            "dayPeriod": "пр.об./сл.об.",
            "endDate": "Крайна дата",
            "era": "ера",
            "hour": "час",
            "minute": "минута",
            "month": "месец",
            "second": "секунда",
            "selectedDateDescription": "e=>\"Избрана дата: \".concat(e.date)",
            "selectedRangeDescription": "e=>\"Избран диапазон: \".concat(e.startDate,\" до \").concat(e.endDate)",
            "selectedTimeDescription": "e=>\"Избрано време: \".concat(e.time)",
            "startDate": "Начална дата",
            "timeZoneName": "часова зона",
            "weekday": "ден от седмицата",
            "year": "година"
        }
    }
}