{
    "exports": {
        "acceptText": "acceptText_b46380",
        "bullet": "bullet_ef82df",
        "bulletWarning": "bulletWarning_b3b85c bullet_ef82df",
        "checkboxOption": "checkboxOption__91358",
        "checklistIcon": "checklistIcon__50333",
        "checklistRow": "checklistRow__76e83",
        "closeButton": "closeButton_c809c0",
        "container": "container__790f8",
        "content": "content__5b1c5",
        "description": "description__852fc",
        "disabled": "disabled__2d361",
        "footer": "footer__468f2",
        "footerImage": "footerImage_e54e7b",
        "form": "form__5ac69",
        "formTitle": "formTitle__87dad",
        "header": "header_b8c1b3",
        "headerCaption": "headerCaption_de9a2a",
        "icon": "icon__298bb",
        "permissionRow": "permissionRow__69477",
        "permissionsTable": "permissionsTable__17d26",
        "roleDot": "roleDot_fbb8dd",
        "roleName": "roleName_e85a2e",
        "roleRow": "roleRow__56c31",
        "table": "table__0a483",
        "tableContainer": "tableContainer__14a9e",
        "tableHeader": "tableHeader_f31e32",
        "updatedForm": "updatedForm__4916a",
        "updatedHeader": "updatedHeader_f41176"
    }
}