{
    "exports": {
        "default": {
            "POPOUT_WINDOW": "popout window",
            "OVERLAY": "overlay",
            "NOTICE": "notice",
            "PREMIUM_UPSELL_TOOLTIP": "premium upsell tooltip",
            "BADGE": "badge",
            "USER_SETTINGS": "user settings",
            "USER_SETTINGS_MENU": "user settings menu",
            "USER_SETTINGS_GIFT_INVENTORY": "user settings gift inventory",
            "ACCOUNT": "account",
            "TEXT_AND_IMAGES": "text and images",
            "GUILD_SETTINGS": "guild settings",
            "OVERVIEW": "overview",
            "STICKERS": "stickers",
            "VANITY_URL": "vanity url",
            "PREMIUM_MARKETING": "premium marketing",
            "PREMIUM_MARKETING_PLAN_COMPARISON": "premium marketing plan comparison",
            "PREMIUM_PAYMENT_MODAL": "premium payment modal",
            "PREMIUM_UPSELL_ALERT": "premium upsell alert",
            "PREMIUM_UPSELL_MODAL": "premium upsell modal",
            "PREMIUM_SETTINGS": "premium settings",
            "PAYMENT_FLOW_TEST_PAGE": "payment flow test page",
            "PREMIUM_PAYMENT_ACTION_SHEET": "premium payment action sheet",
            "CHANNEL_CALL": "channel call",
            "CHANNEL_CALL_CONNECTING_SCREEN": "channel call connecting screen",
            "RTC_PANEL": "rtc panel",
            "SOUNDBOARD_BUTTON": "soundboard button",
            "SOUNDBOARD_POPOUT": "soundboard popout",
            "SOUNDBOARD_WHEEL": "soundboard wheel",
            "SOUNDBOARD_ACTION_SHEET": "soundboard action sheet",
            "GIFT_BUTTON": "gift button",
            "EXPRESSION_SUGGESTIONS": "expression suggestions",
            "EMOJI_PICKER": "emoji picker",
            "STICKER_PICKER": "sticker picker",
            "STICKER_POPOUT": "sticker popout",
            "PREMIUM_UPSELL": "premium upsell",
            "EMPTY_STATE": "empty state",
            "SUBSCRIPTION_DETAILS": "subscription details",
            "SUBSCRIPTION_HEADER": "subscription header",
            "ACCOUNT_CREDIT_BANNER": "account credit banner",
            "PREMIUM_UNCANCEL_MODAL": "premium uncancel modal",
            "PAST_DUE_ONE_TIME_PAYMENT_METHOD_BANNER": "past due one time payment method banner",
            "STREAM_QUALITY_INDICATOR": "stream quality indicator",
            "PREMIUM_TIER_0_TRIAL_ENDING_NOTICE": "premium tier 0 trial ending notice",
            "PREMIUM_TIER_2_TRIAL_ENDING_NOTICE": "premium tier 2 trial ending notice",
            "BOOSTED_GUILD_PERKS_MODAL": "boosted guild perks modal",
            "GUILD_BOOSTING_PREMIUM_UPSELL": "guild boosting premium upsell",
            "RPC": "rpc",
            "BILLING_STANDALONE": "billing standalone",
            "GUILD_CHANNEL_LIST": "guild channel list",
            "GUILD_CHANNEL_LIST_FOOTER": "guild channel list footer",
            "STICKER_MESSAGE": "sticker message",
            "CHANNEL_TEXT_AREA": "channel text area",
            "HEADER_BAR": "header bar",
            "GUILD_ROLE_SUBSCRIPTION_CANCELLATION_MODAL": "guild role subscription cancellation modal",
            "GUILD_ROLE_SUBSCRIPTION_PURCHASE_SYSTEM_MESSAGE": "guild role subscription purchase system message",
            "GUILD_ROLE_SUBSCRIPTION_EMOJI_PICKER_UPSELL": "guild role subscription emoji picker upsell",
            "GUILD_ROLE_SUBSCRIPTION_EMOJI_TEXT_POPOVER_UPSELL": "guild role subscription emoji text popover upsell",
            "PREMIUM_SUBSCRIPTION_CANCELLATION_MODAL": "premium subscription cancellation modal",
            "APPLICATION_SUBSCRIPTION_CANCELLATION_MODAL": "application subscription cancellation modal",
            "PENDING_PLAN_CHANGE_NOTICE": "pending plan change notice",
            "SUBSCRIPTION_CANCEL_DOWNGRADE_MODAL": "subscription cancel downgrade modal",
            "GUILD_HEADER": "guild header",
            "GUILD_BANNER": "guild banner",
            "GUILD_BANNER_NOTICE": "guild banner notice",
            "GUILD_BOOST_PURCHASE_MODAL": "guild boost purchase modal",
            "GUILD_BOOST_CANCELLATION_MODAL": "guild boost cancellation modal",
            "GUILD_BOOST_UNCANCELLATION_MODAL": "guild boost uncancellation modal",
            "GUILD_BOOSTING_PROGRESS_BAR": "guild boosting progress bar",
            "GUILD_BOOSTING_TIER_NONE": "guild boosting tier none",
            "GUILD_BOOSTING_TIER_1": "guild boosting tier 1",
            "GUILD_BOOSTING_TIER_2": "guild boosting tier 2",
            "GUILD_BOOSTING_TIER_3": "guild boosting tier 3",
            "GUILD_BOOSTING_UPSELL_BANNER": "guild boosting upsell banner",
            "GUILD_BOOSTING_SIDEBAR_DISPLAY": "guild boosting sidebar display",
            "GUILDS_LIST": "guilds list",
            "ACTIVITY_CHANNEL_SELECTOR": "activity channel selector",
            "ACTIVITY_DIRECTORY": "activity directory",
            "ACTIVITY_TILE": "activity tile",
            "ACTIVITY_UPSELL": "activity upsell",
            "ACTIVITY_VOICE_CONTROLS_TOGGLE": "activity voice controls toggle",
            "INSTANT_INVITE_MODAL": "instant invite modal",
            "IMAGE_CROPPING_MODAL": "image cropping modal",
            "GIF_PICKER": "gif picker",
            "EXTERNAL_INVITE_LINK_MODAL": "external invite link modal",
            "INVITE_MODAL": "invite modal",
            "INVITE_EMBED": "invite embed",
            "NEW_GUILD_BUTTON": "new guild button",
            "CHARACTER_COUNT": "character count",
            "DM_CHANNEL": "dm channel",
            "GUILD_CHANNEL": "guild channel",
            "FORUM_CHANNEL": "forum channel",
            "FILE_UPLOAD_POPOUT": "file upload popout",
            "EMOJI": "emoji",
            "PROFILE": "profile",
            "PROFILE_MODAL": "profile modal",
            "PROFILE_POPOUT": "profile popout",
            "GUILD_PROFILE": "guild profile",
            "EDIT_AVATAR": "edit avatar",
            "EDIT_BANNER": "edit banner",
            "CHAT_INPUT": "chat input",
            "CREATE_THREAD": "create thread",
            "PREMIUM_PREVIEW_UPSELL_HEADER": "premium preview upsell header",
            "PREMIUM_UPSELL_OVERLAY": "premium upsell overlay",
            "SELECT_IMAGE_MODAL": "select image modal",
            "VIDEO_BACKGROUND_OPTIONS": "video background options",
            "VIDEO_BACKGROUND_IMAGE_OPTION": "video background image option",
            "VIDEO_BACKGROUND_CUSTOM_UPSELL": "video background custom upsell",
            "CAMERA_PREVIEW": "camera preview",
            "HOME_PAGE_PREMIUM_TAB": "home page premium tab",
            "HOME_PAGE_SHOP_TAB": "home page shop tab",
            "PREMIUM_MARKETING_SURFACE": "premium marketing surface",
            "PREMIUM_MARKETING_HERO_CTA": "premium marketing hero cta",
            "PREMIUM_MARKETING_TIER_1_CTA": "premium marketing tier 1 cta",
            "PREMIUM_MARKETING_TIER_2_CTA": "premium marketing tier 2 cta",
            "PREMIUM_MARKETING_LOCALIZED_PRICING_TIER_2_CTA": "premium marketing localized pricing tier 2 cta",
            "PREMIUM_MARKETING_SURFACE_HERO_CTA": "premium marketing surface hero cta",
            "PREMIUM_MARKETING_SURFACE_TIER_2_CTA": "premium marketing surface tier 2 cta",
            "PREMIUM_MARKETING_SURFACE_TIER_1_CTA": "premium marketing surface tier 1 cta",
            "PREMIUM_MARKETING_TIER_CARD": "premium marketing tier card",
            "PREMIUM_MARKETING_PERK_CARD": "premium marketing perk card",
            "PREMIUM_MARKETING_FEATURE": "premium marketing feature",
            "PREMIUM_MARKETING_COMPARISON_TABLE": "premium marketing comparison table",
            "PREMIUM_MARKETING_FOOTER": "premium marketing footer",
            "PREMIUM_MARKETING_GIFT_SECTION": "premium marketing gift section",
            "CHANNEL_CALL_ACTION_BAR": "channel call action bar",
            "AGGREGATE_PREMIUM_UPSELL_MODAL_FEATURE_EMOJI": "aggregate premium upsell modal emoji",
            "AGGREGATE_PREMIUM_UPSELL_MODAL_FEATURE_PROFILE_CUSTOMIZATION": "aggregate premium upsell modal profile customization",
            "AGGREGATE_PREMIUM_UPSELL_MODAL_FEATURE_HD_STREAMING": "aggregate premium upsell modal hd streaming",
            "AGGREGATE_PREMIUM_UPSELL_MODAL_FEATURE_LARGER_FILE_UPLOADS": "aggregate premium upsell modal larger file uploads",
            "AGGREGATE_PREMIUM_UPSELL_MODAL_FEATURE_BOGO": "aggregate premium upsell modal bogo",
            "CHANNEL_EXPANDED_CONTROLS": "channel expanded controls",
            "VOICE_CONTROL_TRAY": "voice control tray",
            "ACTIVE_NOW_COLUMN": "active now column",
            "CONTEXT_MENU": "context menu",
            "CHANNEL_ACTIVITY_FEED_VOICE_MENU": "channel activity feed voice menu",
            "CHANNEL_AUDIT_LOG_MENU": "channel audit log menu",
            "CHANNEL_CATEGORY_MENU": "channel category menu",
            "CHANNEL_LIST_DIRECTORY_CHANNEL_MENU": "channel list menu",
            "CHANNEL_LIST_STORE_CHANNEL_MENU": "channel list store channel menu",
            "CHANNEL_LIST_TEXT_CHANNEL_MENU": "channel list text channel menu",
            "CHANNEL_LIST_THREAD_MENU": "channel list thread menu",
            "CHANNEL_LIST_VOICE_CHANNEL_MENU": "channel list voice channel menu",
            "CHANNEL_TITLE_MENU": "channel title menu",
            "GROUP_DM_MENU": "group dm menu",
            "AUDIT_LOG_USER_MENU": "audit log user menu",
            "BANNED_USER_MENU": "banned user menu",
            "DM_USER_MENU": "dm user menu",
            "GROUP_DM_USER_MENU": "group dm user menu",
            "GUILD_CHANNEL_USER_MENU": "guild channel user menu",
            "GUILD_MODERATION_USER_MENU": "guild moderation user menu",
            "GUILD_MODERATION_RAID_MENU": "guild moderation raid menu",
            "GUILD_SETTINGS_USER_MENU": "guild settings user menu",
            "GUILD_USER_MENU": "guild user menu",
            "THREAD_USER_MENU": "thread user menu",
            "USER_GENERIC_MENU": "user generic menu",
            "USER_PROFILE_ACTIONS_MENU": "user profile actions menu",
            "VOICE_ACTION_SHEET": "voice action sheet",
            "FOCUSED_VOICE_CONTROLS": "focused voice controls",
            "MASKED_LINK": "masked link",
            "LAST_NITRO_HOST_ACTION_SHEET": "last nitro host action sheet",
            "LAST_NITRO_HOST_LEFT_ACTION_SHEET": "last nitro host left action sheet",
            "PREMIUM_TIER_0_ANNOUNCEMENT_ACTION_SHEET": "premium tier 0 announcement action sheet",
            "PS_VOICE_CONNECT_UPSELL": "ps voice connect upsell",
            "PROFILE_THEME_UPSELL_MODAL": "profile theme upsell modal",
            "EDIT_AVATAR_DECORATION_MODAL": "edit avatar decoration modal",
            "EDIT_AVATAR_DECORATION_SHEET": "edit avatar decoration sheet",
            "EDIT_PROFILE_EFFECT_MODAL": "edit profile effect modal",
            "EDIT_PROFILE_EFFECT_ACTION_SHEET": "edit profile effect action sheet",
            "ACCOUNT_PROFILE_POPOUT": "account profile popout",
            "CHANNEL_CALL_OVERFLOW_ACTION_SHEET": "channel_call_overflow_action_sheet",
            "USER_SETTINGS_TRY_OUT_PREMIUM": "user settings try out premium",
            "ACTIVITY_COACH_MARK_NITRO": "activity coach mark nitro",
            "ACTIVITY_COACH_MARK_BOOSTING": "activity coach mark boosting",
            "ACTIVITY_COACH_MARK_HALLOWEEN_2022": "activity coach mark halloween 2022",
            "PREMIUM_TRIAL_TUTORIAL_COACHMARK": "premium trial tutorial coachmark",
            "PREMIUM_TRIAL_TUTORIAL_TOOLTIP": "premium trial tutorial tooltip",
            "ACTIVITY_COACH_MARK_BASH_OUT": "activity coach mark bash out",
            "ACTIVITY_COACH_MARK_POKER": "activity coach mark poker",
            "ACTIVITY_COACH_MARK_GARTIC_PHONE": "activity coach mark gartic phone",
            "ACTIVITIES_COACH_MARK_GAME_NIGHT": "activities coach mark game night",
            "ACTIVITY_COACH_MARK_KRUNKER_STRIKE": "activity coach mark krunker strike",
            "STAGE_VIDEO_LIMIT": "stage video limit",
            "ACTIVITIES_MINI_SHELF": "activities mini shelf",
            "ACTIVITIES_MINI_SHELF_BANNER": "activities mini shelf banner",
            "APP_LAUNCHER": "app launcher",
            "APP_DETAIL": "app detail",
            "VC_TILE_ACTIVITY_INVITE": "vc tile activity invite",
            "VC_TILE_ACTIVITY_SUGGESTION": "vc tile activity suggestion",
            "VC_TILE_ACTIVITY_SHELF_BUTTON": "vc tile activity shelf button",
            "BURST_REACTION_TUTORIAL_COACHMARK": "super reaction tutorial coachmark",
            "APP_ICON_EDITOR": "app icon editor",
            "CLIENT_THEMES_EDITOR": "client themes editor",
            "CLIENT_THEMES_THEME_SELECTOR": "client themes theme selector",
            "AUTOMOD_PROFILE_QUARANTINE_ALERT": "automod profile quarantine alert",
            "SHARE_NITRO_EMBED": "share nitro embed",
            "EMBEDDED_ACTIVITY_MESSAGE": "embedded activity message",
            "REFERRAL_TRIALS_COMPOSER_BUTTON": "referral trials composer button",
            "REFERRAL_TRIALS_POPOUT": "referral trials popout",
            "PREMIUM_MARKETING_ANNOUNCEMENT_MODAL": "premium marketing announcement modal",
            "PREMIUM_MARKETING_PAGE_BANNER": "premium marketing page banner",
            "ACTIVITY_BOOKMARK": "activity bookmark",
            "ACTIVITY_BOOKMARK_LAUNCHER": "activity bookmark launcher",
            "ACTIVITY_INSTANCE_EMBED": "activity instance embed",
            "ACTIVITY_DETAIL_PAGE": "activity detail page",
            "ACTIVITIES_PAGE": "activities page",
            "ACTIVITIES_PAGE_NOTIFICATION_DOT": "activities page cta",
            "ACTIVITIES_PAGE_WHATS_NEW_TILE": "activities page whats new tile",
            "VOICE_PANEL_PRE_JOIN": "voice panel pre-join content",
            "ACTIVITIES_IM_FEELING_LUCKY": "activities im feeling lucky",
            "ACTIVITIES_HAPPENING_NOW": "activities happening now",
            "MEDIA_VIEWER": "media viewer",
            "MESSAGE_LONG_PRESS_MENU": "message long press menu",
            "COLLECTIBLES_SHOP": "collectibles shop",
            "COLLECTIBLES_SHOP_FULLSCREEN": "collectibles shop fullscreen",
            "COLLECTIBLES_SHOP_CARD": "collectibles shop card",
            "COLLECTIBLES_SHOP_CARD_PREVIEW_BUTTON": "collectibles shop card preview button",
            "COLLECTIBLES_SHOP_DETAILS_MODAL": "collectibles shop details modal",
            "COLLECTIBLES_PROFILE_SETTINGS_UPSELL": "collectibles profile settings upsell",
            "COLLECTIBLES_PAYMENT_MODAL": "collectibles payment modal",
            "COLLECTIBLES_COLLECTED_MODAL": "collectibles collected modal",
            "COLLECTIBLES_USER_POPOUT_UPSELL": "collectibles user popout upsell",
            "COLLECTIBLES_FEATURE_EDUCATION_TOOLTIP": "collectibles feature education tooltip",
            "PREMIUM_BILLING_INFO": "premium billing info",
            "PREMIUM_SUBSCRIPTION_DETAILS": "premium subscription details",
            "APP_SUBSCRIPTION_PAYMENT_SOURCE_WITH_INVOICE": "application subscription payment source with invoice",
            "GUILD_BOOST_SLOT_CANCELLATION_MODAL_CURRENT_INVOICE_PREVIEW": "guild boost slot cancellation modal current invoice preview",
            "GUILD_BOOST_SLOT_CANCELLATION_MODAL_RENEWAL_INVOICE_PREVIEW": "guild boost slot cancellation modal renewal invoice preview",
            "GUILD_BOOSTING_REVIEW_PRORATED": "guild boosting review prorated",
            "GUILD_BOOSTING_REVIEW_RENEWAL": "guild boosting review renewal",
            "GUILD_ROLE_SUBSCRIPTION_PAYMENT_SOURCE_WITH_INVOICE": "guild role subscription payment source with invoice",
            "PREMIUM_PLAN_SELECT": "premium_plan_select",
            "CANCEL_INVOICE_PREVIEW": "cancel_invoice_preview",
            "PREMIUM_SUBSCRIPTION_FINE_PRINT_CONTENT": "premium subscription fine print content",
            "SUBSCRIPTION_INVOICE_FOOTER": "subscription invoice footer",
            "BILLING_SWITCH_PLAN_IMMEDIATE_PRORATED_INVOICE_PREVIEW": "billing switch plan immediate prorated invoice preview",
            "BILLING_SWITCH_PLAN_IMMEDIATE_RENEWAL_INVOICE_PREVIEW": "billing switch plan immediate renewal invoice preview",
            "GUILD_BOOSTING_PLAN_SELECT": "GUILD_BOOSTING_PLAN_SELECT",
            "MEMBER_SAFETY_PAGE": "member safety page",
            "GUILD_SETTINGS_MEMBERS_PAGE": "guild settings members page",
            "GUILD_MEMBER_MOD_VIEW": "guild member mod view",
            "GUILD_PRODUCT_EMBED_CARD": "guild product embed card",
            "GUILD_PRODUCT_INFO_MODAL": "guild product info modal",
            "GUILD_PRODUCT_PAYMENT_MODAL": "guild product payment modal",
            "GUILD_SHOP_PAGE": "guild shop page",
            "ACTIVITY_SHELF_ACTIVITY_DETAILS": "activity shelf activty details",
            "MESSAGE_REMIX_TAG": "message remix tag",
            "MESSAGE_REMIX_BUTTON": "message remix button",
            "HAPPENING_NOW_EMBEDDED_ACTIVITY": "happening now embedded activity",
            "CLIPS_SETTINGS": "clips settings",
            "CLIPS_GALLERY": "clips gallery",
            "CLIPS_GALLERY_ITEM": "clips gallery item",
            "CLIPS_EDITOR": "clips editor",
            "CLIPS_SHARE_MODAL": "clips share modal",
            "CHANNEL_ATTACH_BUTTON": "channel attach button",
            "PREMIUM_TRIAL_OFFER_ACTION_SHEET": "premium trial offer action sheet",
            "PREMIUM_SUBSCRIBER_NITRO_HOME": "premium subscriber nitro home",
            "CLYDE_PROFILE_SHARE_MODAL": "clyde profile share modal",
            "GUILD_EVENT_CARD": "guild event card",
            "EVENT_SETTINGS": "event settings",
            "GUILD_EVENT_RSVP_BUTTON": "guild event rsvp button",
            "GIFT_CODE_MODAL": "gift code modal",
            "APP_STOREFRONT": "app storefront"
        }
    }
}